mlalgs/__init__.py
mlalgs/logistic_regression.py
tests/__init__.py
tests/logistic_regression_test.py
mlalgs-0.0.3.dist-info/LICENSE
mlalgs-0.0.3.dist-info/METADATA
mlalgs-0.0.3.dist-info/WHEEL
mlalgs-0.0.3.dist-info/top_level.txt
mlalgs-0.0.3.dist-info/RECORD
